{"id":"segnali-pericolo","title":"2. Segnali di Pericolo","description":"Preannunciano situazioni di pericolo, richiedendo di moderare la velocità.","difficulty":"MEDIUM","tags":["pericolo","triangoli","150m"],"sections":[{"id":"regole-pericolo","subtitle":"Regole Generali","paragraphs":["I segnali di pericolo hanno forma triangolare con vertice verso l'alto, bordo rosso e sfondo bianco.","Sono posti di norma a 150 metri prima del pericolo che segnalano.","Impongono di moderare la velocità in relazione alla visibilità e alle condizioni della strada."],"mnemonics":["Tutti i segnali di pericolo si trovano a 150 metri, tranne la Croce di S. Andrea (immediatamente prima del binario)."]},{"id":"pericoli-strutturali","subtitle":"Pericoli Strutturali della Strada","paragraphs":["Questi segnali indicano anomalie o caratteristiche fisiche della carreggiata che richiedono particolare attenzione."],"images":[{"url":"https://upload.wikimedia.org/wikipedia/commons/e/eb/Italian_traffic_signs_-_strada_deformata_%28figura_II_1%29.svg","caption":"Strada Deformata"},{"url":"https://upload.wikimedia.org/wikipedia/commons/4/42/Italian_traffic_signs_-_dosso.svg","caption":"Dosso"},{"url":"https://upload.wikimedia.org/wikipedia/commons/8/83/Italian_traffic_signs_-_cunetta.svg","caption":"Cunetta"},{"url":"https://upload.wikimedia.org/wikipedia/commons/9/99/Italian_traffic_signs_-_curva_pericolosa_a_destra.svg","caption":"Curva a Destra"},{"url":"https://upload.wikimedia.org/wikipedia/commons/f/fa/Italian_traffic_signs_-_curva_pericolosa_a_sinistra.svg","caption":"Curva a Sinistra"},{"url":"https://upload.wikimedia.org/wikipedia/commons/1/1b/Italian_traffic_signs_-_doppia_curva_dx.svg","caption":"Doppia Curva (prima a Dx)"},{"url":"https://upload.wikimedia.org/wikipedia/commons/d/d1/Italian_traffic_signs_-_passaggio_a_livello_senza_barriere.svg","caption":"Passaggio a Livello (senza barriere)"},{"url":"https://upload.wikimedia.org/wikipedia/commons/5/52/Italian_traffic_signs_-_attraversamento_pedonale.svg","caption":"Attraversamento Pedonale"},{"url":"https://upload.wikimedia.org/wikipedia/commons/8/81/Italian_traffic_signs_-_doppio_senso_di_circolazione_%28figura_II_26%29.svg","caption":"Doppio Senso di Circolazione"}]}]}